odoo9_addon_base_vat_sanitized-9.0.1.0.0-py2.7-nspkg.pth
odoo9_addon_base_vat_sanitized-9.0.1.0.0.dist-info/top_level.txt
odoo9_addon_base_vat_sanitized-9.0.1.0.0.dist-info/WHEEL
odoo9_addon_base_vat_sanitized-9.0.1.0.0.dist-info/RECORD
odoo9_addon_base_vat_sanitized-9.0.1.0.0.dist-info/metadata.json
odoo9_addon_base_vat_sanitized-9.0.1.0.0.dist-info/DESCRIPTION.rst
odoo9_addon_base_vat_sanitized-9.0.1.0.0.dist-info/METADATA
odoo9_addon_base_vat_sanitized-9.0.1.0.0.dist-info/namespace_packages.txt
odoo_addons/base_vat_sanitized/__openerp__.py
odoo_addons/base_vat_sanitized/__init__.py
odoo_addons/base_vat_sanitized/README.rst
odoo_addons/base_vat_sanitized/models/res_partner.py
odoo_addons/base_vat_sanitized/models/__init__.py
odoo_addons/base_vat_sanitized/i18n/es.po
odoo_addons/base_vat_sanitized/i18n/sl.po
odoo_addons/base_vat_sanitized/tests/test_vat.py
odoo_addons/base_vat_sanitized/tests/__init__.py
